{
  "clients": [
    {
      "account_id": "2151825605165694",
      "account_name": "Nunova Health & Image",
      "status": "active",
      "last_7_days": {
        "spend": 598.06,
        "impressions": 23588,
        "clicks": 674,
        "cpc": 0.887329,
        "cpm": 25.354418,
        "ctr": 2.857385,
        "reach": 9940,
        "leads": 23,
        "cost_per_lead": 26.002609
      },
      "last_30_days": {
        "spend": 3572.99,
        "impressions": 109186,
        "clicks": 3354,
        "cpc": 1.065292,
        "cpm": 32.723884,
        "ctr": 3.071822,
        "reach": 23909,
        "leads": 94,
        "cost_per_lead": 38.010532
      }
    },
    {
      "account_id": "1725352711466085",
      "account_name": "AC - AVU Collective",
      "status": "active",
      "last_7_days": {
        "spend": 849.51,
        "impressions": 26916,
        "clicks": 1361,
        "cpc": 0.624181,
        "cpm": 31.561525,
        "ctr": 5.056472,
        "reach": 19730,
        "leads": 45,
        "cost_per_lead": 18.878
      },
      "last_30_days": {
        "spend": 3338.46,
        "impressions": 118427,
        "clicks": 5587,
        "cpc": 0.597541,
        "cpm": 28.190024,
        "ctr": 4.717674,
        "reach": 50972,
        "leads": 184,
        "cost_per_lead": 18.143804
      }
    },
    {
      "account_id": "1306679120584024",
      "account_name": "Beyond Vitaliti",
      "status": "active",
      "last_7_days": {
        "spend": 351.75,
        "impressions": 19650,
        "clicks": 610,
        "cpc": 0.576639,
        "cpm": 17.900763,
        "ctr": 3.104326,
        "reach": 9428,
        "leads": 14,
        "cost_per_lead": 25.125
      },
      "last_30_days": {
        "spend": 1460.24,
        "impressions": 96984,
        "clicks": 3507,
        "cpc": 0.416379,
        "cpm": 15.056504,
        "ctr": 3.61606,
        "reach": 27882,
        "leads": 83,
        "cost_per_lead": 17.593253
      }
    },
    {
      "account_id": "420940994267261",
      "account_name": "Body Slim WLC",
      "status": "active",
      "last_7_days": {
        "spend": 3039.33,
        "impressions": 69956,
        "clicks": 1504,
        "cpc": 2.020831,
        "cpm": 43.446309,
        "ctr": 2.149923,
        "reach": 39176,
        "leads": 20,
        "cost_per_lead": 151.9665
      },
      "last_30_days": {
        "spend": 14853.46,
        "impressions": 366561,
        "clicks": 8274,
        "cpc": 1.795197,
        "cpm": 40.521114,
        "ctr": 2.257196,
        "reach": 125369,
        "leads": 162,
        "cost_per_lead": 91.688025
      }
    },
    {
      "account_id": "497576716728644",
      "account_name": "Body by Lily",
      "status": "active",
      "last_7_days": {
        "spend": 356.2,
        "impressions": 22863,
        "clicks": 701,
        "cpc": 0.508131,
        "cpm": 15.579758,
        "ctr": 3.066089,
        "reach": 14788,
        "leads": 32,
        "cost_per_lead": 11.13125
      },
      "last_30_days": {
        "spend": 1500.99,
        "impressions": 98188,
        "clicks": 2990,
        "cpc": 0.502003,
        "cpm": 15.286899,
        "ctr": 3.045179,
        "reach": 39152,
        "leads": 121,
        "cost_per_lead": 12.404876
      }
    },
    {
      "account_id": "662967109685873",
      "account_name": "Celebrity Body Sculpting",
      "status": "active",
      "last_7_days": {
        "spend": 235.41,
        "impressions": 8479,
        "clicks": 328,
        "cpc": 0.717713,
        "cpm": 27.763887,
        "ctr": 3.868381,
        "reach": 4113,
        "leads": 18,
        "cost_per_lead": 13.078333
      },
      "last_30_days": {
        "spend": 1057.56,
        "impressions": 38048,
        "clicks": 1473,
        "cpc": 0.717963,
        "cpm": 27.795416,
        "ctr": 3.871426,
        "reach": 15809,
        "leads": 117,
        "cost_per_lead": 9.038974
      }
    },
    {
      "account_id": "785026324565387",
      "account_name": "Cloud Chiropractic Servedia",
      "status": "active",
      "last_7_days": {
        "spend": 345.76,
        "impressions": 11165,
        "clicks": 432,
        "cpc": 0.80037,
        "cpm": 30.968204,
        "ctr": 3.869234,
        "reach": 7198,
        "leads": 10,
        "cost_per_lead": 34.576
      },
      "last_30_days": {
        "spend": 1196.65,
        "impressions": 46877,
        "clicks": 1853,
        "cpc": 0.645791,
        "cpm": 25.527444,
        "ctr": 3.952898,
        "reach": 21228,
        "leads": 59,
        "cost_per_lead": 20.282203
      }
    },
    {
      "account_id": "1108581597844624",
      "account_name": "Cosmetic Surgery Of New York - SA",
      "status": "no_data",
      "last_7_days": {
        "spend": 0.0,
        "impressions": 0,
        "clicks": 0,
        "cpc": 0.0,
        "cpm": 0.0,
        "ctr": 0.0,
        "reach": 0,
        "leads": 0,
        "cost_per_lead": 0
      },
      "last_30_days": {
        "spend": 0.0,
        "impressions": 0,
        "clicks": 0,
        "cpc": 0.0,
        "cpm": 0.0,
        "ctr": 0.0,
        "reach": 0,
        "leads": 0,
        "cost_per_lead": 0
      }
    },
    {
      "account_id": "1072278307590785",
      "account_name": "Cosmetico - SA",
      "status": "active",
      "last_7_days": {
        "spend": 351.79,
        "impressions": 11543,
        "clicks": 473,
        "cpc": 0.743742,
        "cpm": 30.476479,
        "ctr": 4.097722,
        "reach": 6877,
        "leads": 18,
        "cost_per_lead": 19.543889
      },
      "last_30_days": {
        "spend": 1502.85,
        "impressions": 59205,
        "clicks": 2452,
        "cpc": 0.612908,
        "cpm": 25.383836,
        "ctr": 4.141542,
        "reach": 21318,
        "leads": 116,
        "cost_per_lead": 12.955603
      }
    },
    {
      "account_id": "283412697676323",
      "account_name": "Dr. Michelle Zubair",
      "status": "no_data",
      "last_7_days": {
        "spend": 0.0,
        "impressions": 0,
        "clicks": 0,
        "cpc": 0.0,
        "cpm": 0.0,
        "ctr": 0.0,
        "reach": 0,
        "leads": 0,
        "cost_per_lead": 0
      },
      "last_30_days": {
        "spend": 0.0,
        "impressions": 0,
        "clicks": 0,
        "cpc": 0.0,
        "cpm": 0.0,
        "ctr": 0.0,
        "reach": 0,
        "leads": 0,
        "cost_per_lead": 0
      }
    },
    {
      "account_id": "1837871783720841",
      "account_name": "Ensoul Aesthetics And Wellness - SA",
      "status": "no_data",
      "last_7_days": {
        "spend": 0.0,
        "impressions": 0,
        "clicks": 0,
        "cpc": 0.0,
        "cpm": 0.0,
        "ctr": 0.0,
        "reach": 0,
        "leads": 0,
        "cost_per_lead": 0
      },
      "last_30_days": {
        "spend": 368.72,
        "impressions": 23854,
        "clicks": 511,
        "cpc": 0.721566,
        "cpm": 15.457366,
        "ctr": 2.142198,
        "reach": 13480,
        "leads": 31,
        "cost_per_lead": 11.894194
      }
    },
    {
      "account_id": "404232133542932",
      "account_name": "Golden Health & Beauty",
      "status": "active",
      "last_7_days": {
        "spend": 787.11,
        "impressions": 18988,
        "clicks": 627,
        "cpc": 1.255359,
        "cpm": 41.453023,
        "ctr": 3.302086,
        "reach": 11199,
        "leads": 24,
        "cost_per_lead": 32.79625
      },
      "last_30_days": {
        "spend": 2207.15,
        "impressions": 55541,
        "clicks": 2186,
        "cpc": 1.009675,
        "cpm": 39.739112,
        "ctr": 3.935831,
        "reach": 21232,
        "leads": 85,
        "cost_per_lead": 25.966471
      }
    },
    {
      "account_id": "1230444507356265",
      "account_name": "Healthpreneur",
      "status": "no_data",
      "last_7_days": {
        "spend": 0.0,
        "impressions": 0,
        "clicks": 0,
        "cpc": 0.0,
        "cpm": 0.0,
        "ctr": 0.0,
        "reach": 0,
        "leads": 0,
        "cost_per_lead": 0
      },
      "last_30_days": {
        "spend": 0.0,
        "impressions": 0,
        "clicks": 0,
        "cpc": 0.0,
        "cpm": 0.0,
        "ctr": 0.0,
        "reach": 0,
        "leads": 0,
        "cost_per_lead": 0
      }
    },
    {
      "account_id": "813563481027887",
      "account_name": "Heritage Wellness and Medspa",
      "status": "active",
      "last_7_days": {
        "spend": 88.18,
        "impressions": 2067,
        "clicks": 95,
        "cpc": 0.928211,
        "cpm": 42.660861,
        "ctr": 4.596033,
        "reach": 1657,
        "leads": 5,
        "cost_per_lead": 17.636
      },
      "last_30_days": {
        "spend": 88.18,
        "impressions": 2067,
        "clicks": 95,
        "cpc": 0.928211,
        "cpm": 42.660861,
        "ctr": 4.596033,
        "reach": 1657,
        "leads": 5,
        "cost_per_lead": 17.636
      }
    },
    {
      "account_id": "1566788920935861",
      "account_name": "Iconic Laser",
      "status": "no_data",
      "last_7_days": {
        "spend": 0.0,
        "impressions": 0,
        "clicks": 0,
        "cpc": 0.0,
        "cpm": 0.0,
        "ctr": 0.0,
        "reach": 0,
        "leads": 0,
        "cost_per_lead": 0
      },
      "last_30_days": {
        "spend": 0.0,
        "impressions": 0,
        "clicks": 0,
        "cpc": 0.0,
        "cpm": 0.0,
        "ctr": 0.0,
        "reach": 0,
        "leads": 0,
        "cost_per_lead": 0
      }
    },
    {
      "account_id": "571905160084946",
      "account_name": "Ideal Weightloss",
      "status": "active",
      "last_7_days": {
        "spend": 139.16,
        "impressions": 7709,
        "clicks": 218,
        "cpc": 0.638349,
        "cpm": 18.051628,
        "ctr": 2.827864,
        "reach": 3296,
        "leads": 0,
        "cost_per_lead": 0
      },
      "last_30_days": {
        "spend": 1215.22,
        "impressions": 61239,
        "clicks": 1407,
        "cpc": 0.863696,
        "cpm": 19.84389,
        "ctr": 2.297555,
        "reach": 15948,
        "leads": 1,
        "cost_per_lead": 1215.22
      }
    },
    {
      "account_id": "1108868149742936",
      "account_name": "Jule's Fibroblast & Body Contour",
      "status": "active",
      "last_7_days": {
        "spend": 141.88,
        "impressions": 3145,
        "clicks": 111,
        "cpc": 1.278198,
        "cpm": 45.112878,
        "ctr": 3.529412,
        "reach": 2737,
        "leads": 3,
        "cost_per_lead": 47.293333
      },
      "last_30_days": {
        "spend": 809.63,
        "impressions": 21304,
        "clicks": 854,
        "cpc": 0.948045,
        "cpm": 38.003661,
        "ctr": 4.008637,
        "reach": 11145,
        "leads": 33,
        "cost_per_lead": 24.534242
      }
    },
    {
      "account_id": "1033045841275568",
      "account_name": "Luminous Laser and Skin Spa",
      "status": "active",
      "last_7_days": {
        "spend": 196.36,
        "impressions": 10723,
        "clicks": 309,
        "cpc": 0.635469,
        "cpm": 18.31204,
        "ctr": 2.881656,
        "reach": 8014,
        "leads": 10,
        "cost_per_lead": 19.636
      },
      "last_30_days": {
        "spend": 1194.27,
        "impressions": 53986,
        "clicks": 1569,
        "cpc": 0.761166,
        "cpm": 22.121846,
        "ctr": 2.906309,
        "reach": 25121,
        "leads": 68,
        "cost_per_lead": 17.562794
      }
    },
    {
      "account_id": "947326761106052",
      "account_name": "MLA Ad Account",
      "status": "active",
      "last_7_days": {
        "spend": 87.47,
        "impressions": 6869,
        "clicks": 80,
        "cpc": 1.093375,
        "cpm": 12.734022,
        "ctr": 1.164653,
        "reach": 6311,
        "leads": 0,
        "cost_per_lead": 0
      },
      "last_30_days": {
        "spend": 742.52,
        "impressions": 20568,
        "clicks": 660,
        "cpc": 1.12503,
        "cpm": 36.100739,
        "ctr": 3.208868,
        "reach": 14667,
        "leads": 9,
        "cost_per_lead": 82.502222
      }
    },
    {
      "account_id": "1795278261246132",
      "account_name": "McQuiston Dental & Aesthetics",
      "status": "active",
      "last_7_days": {
        "spend": 358.99,
        "impressions": 8620,
        "clicks": 573,
        "cpc": 0.62651,
        "cpm": 41.646172,
        "ctr": 6.647332,
        "reach": 5917,
        "leads": 19,
        "cost_per_lead": 18.894211
      },
      "last_30_days": {
        "spend": 1499.61,
        "impressions": 35948,
        "clicks": 2142,
        "cpc": 0.700098,
        "cpm": 41.71609,
        "ctr": 5.958607,
        "reach": 16577,
        "leads": 130,
        "cost_per_lead": 11.535462
      }
    },
    {
      "account_id": "873011548816017",
      "account_name": "Michel Medspa - Dana Point",
      "status": "active",
      "last_7_days": {
        "spend": 152.46,
        "impressions": 1443,
        "clicks": 38,
        "cpc": 4.012105,
        "cpm": 105.654886,
        "ctr": 2.633403,
        "reach": 1059,
        "leads": 2,
        "cost_per_lead": 76.23
      },
      "last_30_days": {
        "spend": 3063.07,
        "impressions": 54478,
        "clicks": 1464,
        "cpc": 2.092261,
        "cpm": 56.225816,
        "ctr": 2.687323,
        "reach": 21478,
        "leads": 57,
        "cost_per_lead": 53.73807
      }
    },
    {
      "account_id": "624982636077867",
      "account_name": "Precision Weight Loss",
      "status": "active",
      "last_7_days": {
        "spend": 535.72,
        "impressions": 12019,
        "clicks": 567,
        "cpc": 0.944832,
        "cpm": 44.57276,
        "ctr": 4.717531,
        "reach": 8085,
        "leads": 24,
        "cost_per_lead": 22.321667
      },
      "last_30_days": {
        "spend": 2072.47,
        "impressions": 48981,
        "clicks": 2341,
        "cpc": 0.885293,
        "cpm": 42.311713,
        "ctr": 4.779404,
        "reach": 24258,
        "leads": 73,
        "cost_per_lead": 28.39
      }
    },
    {
      "account_id": "664585076610096",
      "account_name": "Prestige Laser & Skin Clinic",
      "status": "active",
      "last_7_days": {
        "spend": 352.65,
        "impressions": 21367,
        "clicks": 734,
        "cpc": 0.48045,
        "cpm": 16.504423,
        "ctr": 3.435204,
        "reach": 12505,
        "leads": 28,
        "cost_per_lead": 12.594643
      },
      "last_30_days": {
        "spend": 1497.65,
        "impressions": 91071,
        "clicks": 2925,
        "cpc": 0.512017,
        "cpm": 16.444862,
        "ctr": 3.21178,
        "reach": 33636,
        "leads": 113,
        "cost_per_lead": 13.25354
      }
    },
    {
      "account_id": "510154927988642",
      "account_name": "Servedia - B2B - CHF",
      "status": "active",
      "last_7_days": {
        "spend": 5885.43,
        "impressions": 278839,
        "clicks": 1448,
        "cpc": 4.064523,
        "cpm": 21.106911,
        "ctr": 0.519296,
        "reach": 229440,
        "leads": 69,
        "cost_per_lead": 85.296087
      },
      "last_30_days": {
        "spend": 21521.88,
        "impressions": 1151288,
        "clicks": 6383,
        "cpc": 3.37175,
        "cpm": 18.693741,
        "ctr": 0.554423,
        "reach": 742912,
        "leads": 277,
        "cost_per_lead": 77.696318
      }
    },
    {
      "account_id": "3896645637242883",
      "account_name": "Servedia - Hiring - CHF",
      "status": "no_data",
      "last_7_days": {
        "spend": 0.0,
        "impressions": 0,
        "clicks": 0,
        "cpc": 0.0,
        "cpm": 0.0,
        "ctr": 0.0,
        "reach": 0,
        "leads": 0,
        "cost_per_lead": 0
      },
      "last_30_days": {
        "spend": 0.0,
        "impressions": 0,
        "clicks": 0,
        "cpc": 0.0,
        "cpm": 0.0,
        "ctr": 0.0,
        "reach": 0,
        "leads": 0,
        "cost_per_lead": 0
      }
    },
    {
      "account_id": "524158318772571",
      "account_name": "Skinholic(2025) - AIMOP",
      "status": "no_data",
      "last_7_days": {
        "spend": 0.0,
        "impressions": 0,
        "clicks": 0,
        "cpc": 0.0,
        "cpm": 0.0,
        "ctr": 0.0,
        "reach": 0,
        "leads": 0,
        "cost_per_lead": 0
      },
      "last_30_days": {
        "spend": 170.24,
        "impressions": 11615,
        "clicks": 509,
        "cpc": 0.33446,
        "cpm": 14.656909,
        "ctr": 4.382264,
        "reach": 4565,
        "leads": 0,
        "cost_per_lead": 0
      }
    },
    {
      "account_id": "4140577459602242",
      "account_name": "Skinsation Aesthetics - SA",
      "status": "active",
      "last_7_days": {
        "spend": 490.78,
        "impressions": 8114,
        "clicks": 265,
        "cpc": 1.852,
        "cpm": 60.48558,
        "ctr": 3.26596,
        "reach": 4269,
        "leads": 9,
        "cost_per_lead": 54.531111
      },
      "last_30_days": {
        "spend": 1699.55,
        "impressions": 41777,
        "clicks": 1542,
        "cpc": 1.102173,
        "cpm": 40.681475,
        "ctr": 3.691026,
        "reach": 16560,
        "leads": 56,
        "cost_per_lead": 30.349107
      }
    },
    {
      "account_id": "502049325517257",
      "account_name": "The MAC OKC",
      "status": "active",
      "last_7_days": {
        "spend": 756.78,
        "impressions": 10012,
        "clicks": 541,
        "cpc": 1.398854,
        "cpm": 75.587295,
        "ctr": 5.403516,
        "reach": 8451,
        "leads": 19,
        "cost_per_lead": 39.830526
      },
      "last_30_days": {
        "spend": 3743.91,
        "impressions": 57560,
        "clicks": 2883,
        "cpc": 1.298616,
        "cpm": 65.043607,
        "ctr": 5.008687,
        "reach": 37972,
        "leads": 118,
        "cost_per_lead": 31.728051
      }
    },
    {
      "account_id": "1603057050496702",
      "account_name": "Thorpe Wellness 2.0",
      "status": "no_data",
      "last_7_days": {
        "spend": 0.0,
        "impressions": 0,
        "clicks": 0,
        "cpc": 0.0,
        "cpm": 0.0,
        "ctr": 0.0,
        "reach": 0,
        "leads": 0,
        "cost_per_lead": 0
      },
      "last_30_days": {
        "spend": 0.0,
        "impressions": 0,
        "clicks": 0,
        "cpc": 0.0,
        "cpm": 0.0,
        "ctr": 0.0,
        "reach": 0,
        "leads": 0,
        "cost_per_lead": 0
      }
    },
    {
      "account_id": "1242208869314128",
      "account_name": "Transformations Esthetics & Wellness",
      "status": "active",
      "last_7_days": {
        "spend": 357.03,
        "impressions": 9103,
        "clicks": 322,
        "cpc": 1.108789,
        "cpm": 39.221136,
        "ctr": 3.537295,
        "reach": 4155,
        "leads": 11,
        "cost_per_lead": 32.457273
      },
      "last_30_days": {
        "spend": 1482.62,
        "impressions": 63203,
        "clicks": 1958,
        "cpc": 0.757211,
        "cpm": 23.458064,
        "ctr": 3.097954,
        "reach": 25392,
        "leads": 42,
        "cost_per_lead": 35.300476
      }
    },
    {
      "account_id": "982882907385968",
      "account_name": "Transformative Wellness",
      "status": "active",
      "last_7_days": {
        "spend": 412.94,
        "impressions": 8097,
        "clicks": 194,
        "cpc": 2.128557,
        "cpm": 50.999135,
        "ctr": 2.395949,
        "reach": 3905,
        "leads": 10,
        "cost_per_lead": 41.294
      },
      "last_30_days": {
        "spend": 865.91,
        "impressions": 16012,
        "clicks": 416,
        "cpc": 2.081514,
        "cpm": 54.078816,
        "ctr": 2.598051,
        "reach": 6401,
        "leads": 24,
        "cost_per_lead": 36.079583
      }
    },
    {
      "account_id": "1488627745841127",
      "account_name": "Vital Life",
      "status": "active",
      "last_7_days": {
        "spend": 365.54,
        "impressions": 9574,
        "clicks": 343,
        "cpc": 1.065714,
        "cpm": 38.180489,
        "ctr": 3.58262,
        "reach": 4753,
        "leads": 12,
        "cost_per_lead": 30.461667
      },
      "last_30_days": {
        "spend": 1418.47,
        "impressions": 55986,
        "clicks": 2459,
        "cpc": 0.576848,
        "cpm": 25.336155,
        "ctr": 4.392169,
        "reach": 26391,
        "leads": 71,
        "cost_per_lead": 19.978451
      }
    },
    {
      "account_id": "894241480205692",
      "account_name": "Wellness Herbal - SA",
      "status": "active",
      "last_7_days": {
        "spend": 350.92,
        "impressions": 9654,
        "clicks": 251,
        "cpc": 1.398088,
        "cpm": 36.3497,
        "ctr": 2.599959,
        "reach": 6539,
        "leads": 12,
        "cost_per_lead": 29.243333
      },
      "last_30_days": {
        "spend": 1486.92,
        "impressions": 40723,
        "clicks": 1246,
        "cpc": 1.193355,
        "cpm": 36.513027,
        "ctr": 3.059696,
        "reach": 19651,
        "leads": 62,
        "cost_per_lead": 23.982581
      }
    },
    {
      "account_id": "1121472973270105",
      "account_name": "Wilmarwell LLC",
      "status": "no_data",
      "last_7_days": {
        "spend": 0.0,
        "impressions": 0,
        "clicks": 0,
        "cpc": 0.0,
        "cpm": 0.0,
        "ctr": 0.0,
        "reach": 0,
        "leads": 0,
        "cost_per_lead": 0
      },
      "last_30_days": {
        "spend": 0.0,
        "impressions": 0,
        "clicks": 0,
        "cpc": 0.0,
        "cpm": 0.0,
        "ctr": 0.0,
        "reach": 0,
        "leads": 0,
        "cost_per_lead": 0
      }
    },
    {
      "account_id": "1400828974006140",
      "account_name": "beautyandwellnesscenter",
      "status": "active",
      "last_7_days": {
        "spend": 358.89,
        "impressions": 16822,
        "clicks": 666,
        "cpc": 0.538874,
        "cpm": 21.334562,
        "ctr": 3.959101,
        "reach": 9821,
        "leads": 39,
        "cost_per_lead": 9.202308
      },
      "last_30_days": {
        "spend": 1493.5,
        "impressions": 71434,
        "clicks": 2781,
        "cpc": 0.537037,
        "cpm": 20.907411,
        "ctr": 3.893104,
        "reach": 24445,
        "leads": 128,
        "cost_per_lead": 11.667969
      }
    },
    {
      "account_id": "1464948185130737",
      "account_name": "dailey aesthetics",
      "status": "active",
      "last_7_days": {
        "spend": 175.01,
        "impressions": 2775,
        "clicks": 118,
        "cpc": 1.483136,
        "cpm": 63.066667,
        "ctr": 4.252252,
        "reach": 2241,
        "leads": 4,
        "cost_per_lead": 43.7525
      },
      "last_30_days": {
        "spend": 182.47,
        "impressions": 2871,
        "clicks": 122,
        "cpc": 1.495656,
        "cpm": 63.556252,
        "ctr": 4.24939,
        "reach": 2297,
        "leads": 4,
        "cost_per_lead": 45.6175
      }
    },
    {
      "account_id": "890702377151942",
      "account_name": "servedia - gencore aesthetic",
      "status": "active",
      "last_7_days": {
        "spend": 467.66,
        "impressions": 9029,
        "clicks": 368,
        "cpc": 1.270815,
        "cpm": 51.795326,
        "ctr": 4.075756,
        "reach": 4452,
        "leads": 14,
        "cost_per_lead": 33.404286
      },
      "last_30_days": {
        "spend": 1796.0,
        "impressions": 42778,
        "clicks": 1988,
        "cpc": 0.903421,
        "cpm": 41.984197,
        "ctr": 4.647249,
        "reach": 12661,
        "leads": 80,
        "cost_per_lead": 22.45
      }
    }
  ],
  "total_accounts": 37,
  "accounts_with_data": 28,
  "accounts_with_errors": 0,
  "errors": [],
  "pulled_at": "2026-04-05T09:29:39Z"
}