{
  "clients": [
    {
      "account_id": "2151825605165694",
      "account_name": "Nunova Health & Image",
      "status": "active",
      "last_7_days": {
        "spend": 638.6,
        "impressions": 25240,
        "clicks": 718,
        "cpc": 0.889415,
        "cpm": 25.301109,
        "ctr": 2.844691,
        "reach": 10347,
        "leads": 25,
        "cost_per_lead": 25.544
      },
      "last_30_days": {
        "spend": 3613.53,
        "impressions": 110838,
        "clicks": 3398,
        "cpc": 1.063428,
        "cpm": 32.601905,
        "ctr": 3.065736,
        "reach": 24245,
        "leads": 96,
        "cost_per_lead": 37.640938
      }
    },
    {
      "account_id": "1725352711466085",
      "account_name": "AC - AVU Collective",
      "status": "active",
      "last_7_days": {
        "spend": 939.78,
        "impressions": 30137,
        "clicks": 1528,
        "cpc": 0.615039,
        "cpm": 31.183595,
        "ctr": 5.07018,
        "reach": 21397,
        "leads": 52,
        "cost_per_lead": 18.072692
      },
      "last_30_days": {
        "spend": 3428.73,
        "impressions": 121648,
        "clicks": 5754,
        "cpc": 0.595886,
        "cpm": 28.185667,
        "ctr": 4.730041,
        "reach": 51751,
        "leads": 191,
        "cost_per_lead": 17.951466
      }
    },
    {
      "account_id": "1306679120584024",
      "account_name": "Beyond Vitaliti",
      "status": "active",
      "last_7_days": {
        "spend": 380.61,
        "impressions": 21090,
        "clicks": 661,
        "cpc": 0.575809,
        "cpm": 18.046942,
        "ctr": 3.134187,
        "reach": 9798,
        "leads": 16,
        "cost_per_lead": 23.788125
      },
      "last_30_days": {
        "spend": 1489.1,
        "impressions": 98424,
        "clicks": 3558,
        "cpc": 0.418522,
        "cpm": 15.12944,
        "ctr": 3.614972,
        "reach": 28031,
        "leads": 85,
        "cost_per_lead": 17.518824
      }
    },
    {
      "account_id": "420940994267261",
      "account_name": "Body Slim WLC",
      "status": "active",
      "last_7_days": {
        "spend": 3457.41,
        "impressions": 78964,
        "clicks": 1676,
        "cpc": 2.062894,
        "cpm": 43.784636,
        "ctr": 2.122486,
        "reach": 42942,
        "leads": 25,
        "cost_per_lead": 138.2964
      },
      "last_30_days": {
        "spend": 15271.54,
        "impressions": 375569,
        "clicks": 8446,
        "cpc": 1.808139,
        "cpm": 40.662408,
        "ctr": 2.248854,
        "reach": 128198,
        "leads": 167,
        "cost_per_lead": 91.446347
      }
    },
    {
      "account_id": "497576716728644",
      "account_name": "Body by Lily",
      "status": "active",
      "last_7_days": {
        "spend": 386.72,
        "impressions": 25069,
        "clicks": 768,
        "cpc": 0.503542,
        "cpm": 15.426224,
        "ctr": 3.063545,
        "reach": 15798,
        "leads": 36,
        "cost_per_lead": 10.742222
      },
      "last_30_days": {
        "spend": 1531.51,
        "impressions": 100394,
        "clicks": 3057,
        "cpc": 0.500985,
        "cpm": 15.254995,
        "ctr": 3.045003,
        "reach": 39921,
        "leads": 125,
        "cost_per_lead": 12.25208
      }
    },
    {
      "account_id": "662967109685873",
      "account_name": "Celebrity Body Sculpting",
      "status": "active",
      "last_7_days": {
        "spend": 235.41,
        "impressions": 8479,
        "clicks": 328,
        "cpc": 0.717713,
        "cpm": 27.763887,
        "ctr": 3.868381,
        "reach": 4113,
        "leads": 18,
        "cost_per_lead": 13.078333
      },
      "last_30_days": {
        "spend": 1057.56,
        "impressions": 38048,
        "clicks": 1473,
        "cpc": 0.717963,
        "cpm": 27.795416,
        "ctr": 3.871426,
        "reach": 15809,
        "leads": 117,
        "cost_per_lead": 9.038974
      }
    },
    {
      "account_id": "785026324565387",
      "account_name": "Cloud Chiropractic Servedia",
      "status": "active",
      "last_7_days": {
        "spend": 376.2,
        "impressions": 12301,
        "clicks": 487,
        "cpc": 0.772485,
        "cpm": 30.582879,
        "ctr": 3.959028,
        "reach": 7708,
        "leads": 10,
        "cost_per_lead": 37.62
      },
      "last_30_days": {
        "spend": 1227.09,
        "impressions": 48013,
        "clicks": 1908,
        "cpc": 0.643129,
        "cpm": 25.557453,
        "ctr": 3.973924,
        "reach": 21571,
        "leads": 59,
        "cost_per_lead": 20.798136
      }
    },
    {
      "account_id": "1108581597844624",
      "account_name": "Cosmetic Surgery Of New York - SA",
      "status": "no_data",
      "last_7_days": {
        "spend": 0.0,
        "impressions": 0,
        "clicks": 0,
        "cpc": 0.0,
        "cpm": 0.0,
        "ctr": 0.0,
        "reach": 0,
        "leads": 0,
        "cost_per_lead": 0
      },
      "last_30_days": {
        "spend": 0.0,
        "impressions": 0,
        "clicks": 0,
        "cpc": 0.0,
        "cpm": 0.0,
        "ctr": 0.0,
        "reach": 0,
        "leads": 0,
        "cost_per_lead": 0
      }
    },
    {
      "account_id": "1072278307590785",
      "account_name": "Cosmetico - SA",
      "status": "active",
      "last_7_days": {
        "spend": 387.61,
        "impressions": 12896,
        "clicks": 527,
        "cpc": 0.735503,
        "cpm": 30.056607,
        "ctr": 4.086538,
        "reach": 7509,
        "leads": 20,
        "cost_per_lead": 19.3805
      },
      "last_30_days": {
        "spend": 1538.67,
        "impressions": 60558,
        "clicks": 2506,
        "cpc": 0.613994,
        "cpm": 25.408204,
        "ctr": 4.138182,
        "reach": 21675,
        "leads": 118,
        "cost_per_lead": 13.039576
      }
    },
    {
      "account_id": "283412697676323",
      "account_name": "Dr. Michelle Zubair",
      "status": "no_data",
      "last_7_days": {
        "spend": 0.0,
        "impressions": 0,
        "clicks": 0,
        "cpc": 0.0,
        "cpm": 0.0,
        "ctr": 0.0,
        "reach": 0,
        "leads": 0,
        "cost_per_lead": 0
      },
      "last_30_days": {
        "spend": 0.0,
        "impressions": 0,
        "clicks": 0,
        "cpc": 0.0,
        "cpm": 0.0,
        "ctr": 0.0,
        "reach": 0,
        "leads": 0,
        "cost_per_lead": 0
      }
    },
    {
      "account_id": "1837871783720841",
      "account_name": "Ensoul Aesthetics And Wellness - SA",
      "status": "no_data",
      "last_7_days": {
        "spend": 0.0,
        "impressions": 0,
        "clicks": 0,
        "cpc": 0.0,
        "cpm": 0.0,
        "ctr": 0.0,
        "reach": 0,
        "leads": 0,
        "cost_per_lead": 0
      },
      "last_30_days": {
        "spend": 368.72,
        "impressions": 23854,
        "clicks": 511,
        "cpc": 0.721566,
        "cpm": 15.457366,
        "ctr": 2.142198,
        "reach": 13480,
        "leads": 31,
        "cost_per_lead": 11.894194
      }
    },
    {
      "account_id": "404232133542932",
      "account_name": "Golden Health & Beauty",
      "status": "active",
      "last_7_days": {
        "spend": 787.11,
        "impressions": 18988,
        "clicks": 627,
        "cpc": 1.255359,
        "cpm": 41.453023,
        "ctr": 3.302086,
        "reach": 11199,
        "leads": 24,
        "cost_per_lead": 32.79625
      },
      "last_30_days": {
        "spend": 2207.15,
        "impressions": 55541,
        "clicks": 2186,
        "cpc": 1.009675,
        "cpm": 39.739112,
        "ctr": 3.935831,
        "reach": 21232,
        "leads": 85,
        "cost_per_lead": 25.966471
      }
    },
    {
      "account_id": "1230444507356265",
      "account_name": "Healthpreneur",
      "status": "no_data",
      "last_7_days": {
        "spend": 0.0,
        "impressions": 0,
        "clicks": 0,
        "cpc": 0.0,
        "cpm": 0.0,
        "ctr": 0.0,
        "reach": 0,
        "leads": 0,
        "cost_per_lead": 0
      },
      "last_30_days": {
        "spend": 0.0,
        "impressions": 0,
        "clicks": 0,
        "cpc": 0.0,
        "cpm": 0.0,
        "ctr": 0.0,
        "reach": 0,
        "leads": 0,
        "cost_per_lead": 0
      }
    },
    {
      "account_id": "813563481027887",
      "account_name": "Heritage Wellness and Medspa",
      "status": "active",
      "last_7_days": {
        "spend": 133.47,
        "impressions": 3227,
        "clicks": 141,
        "cpc": 0.946596,
        "cpm": 41.360397,
        "ctr": 4.369383,
        "reach": 2385,
        "leads": 10,
        "cost_per_lead": 13.347
      },
      "last_30_days": {
        "spend": 133.47,
        "impressions": 3227,
        "clicks": 141,
        "cpc": 0.946596,
        "cpm": 41.360397,
        "ctr": 4.369383,
        "reach": 2385,
        "leads": 10,
        "cost_per_lead": 13.347
      }
    },
    {
      "account_id": "1566788920935861",
      "account_name": "Iconic Laser",
      "status": "no_data",
      "last_7_days": {
        "spend": 0.0,
        "impressions": 0,
        "clicks": 0,
        "cpc": 0.0,
        "cpm": 0.0,
        "ctr": 0.0,
        "reach": 0,
        "leads": 0,
        "cost_per_lead": 0
      },
      "last_30_days": {
        "spend": 0.0,
        "impressions": 0,
        "clicks": 0,
        "cpc": 0.0,
        "cpm": 0.0,
        "ctr": 0.0,
        "reach": 0,
        "leads": 0,
        "cost_per_lead": 0
      }
    },
    {
      "account_id": "571905160084946",
      "account_name": "Ideal Weightloss",
      "status": "active",
      "last_7_days": {
        "spend": 153.32,
        "impressions": 8561,
        "clicks": 236,
        "cpc": 0.649661,
        "cpm": 17.909123,
        "ctr": 2.756687,
        "reach": 3528,
        "leads": 0,
        "cost_per_lead": 0
      },
      "last_30_days": {
        "spend": 1229.38,
        "impressions": 62091,
        "clicks": 1425,
        "cpc": 0.862723,
        "cpm": 19.799649,
        "ctr": 2.295019,
        "reach": 16056,
        "leads": 1,
        "cost_per_lead": 1229.38
      }
    },
    {
      "account_id": "1108868149742936",
      "account_name": "Jule's Fibroblast & Body Contour",
      "status": "active",
      "last_7_days": {
        "spend": 160.42,
        "impressions": 3600,
        "clicks": 126,
        "cpc": 1.273175,
        "cpm": 44.561111,
        "ctr": 3.5,
        "reach": 3003,
        "leads": 3,
        "cost_per_lead": 53.473333
      },
      "last_30_days": {
        "spend": 828.17,
        "impressions": 21759,
        "clicks": 869,
        "cpc": 0.953015,
        "cpm": 38.061032,
        "ctr": 3.99375,
        "reach": 11260,
        "leads": 33,
        "cost_per_lead": 25.096061
      }
    },
    {
      "account_id": "1033045841275568",
      "account_name": "Luminous Laser and Skin Spa",
      "status": "active",
      "last_7_days": {
        "spend": 196.36,
        "impressions": 10723,
        "clicks": 309,
        "cpc": 0.635469,
        "cpm": 18.31204,
        "ctr": 2.881656,
        "reach": 8014,
        "leads": 10,
        "cost_per_lead": 19.636
      },
      "last_30_days": {
        "spend": 1194.27,
        "impressions": 53986,
        "clicks": 1569,
        "cpc": 0.761166,
        "cpm": 22.121846,
        "ctr": 2.906309,
        "reach": 25121,
        "leads": 68,
        "cost_per_lead": 17.562794
      }
    },
    {
      "account_id": "947326761106052",
      "account_name": "MLA Ad Account",
      "status": "active",
      "last_7_days": {
        "spend": 87.47,
        "impressions": 6869,
        "clicks": 80,
        "cpc": 1.093375,
        "cpm": 12.734022,
        "ctr": 1.164653,
        "reach": 6311,
        "leads": 0,
        "cost_per_lead": 0
      },
      "last_30_days": {
        "spend": 742.52,
        "impressions": 20568,
        "clicks": 660,
        "cpc": 1.12503,
        "cpm": 36.100739,
        "ctr": 3.208868,
        "reach": 14667,
        "leads": 9,
        "cost_per_lead": 82.502222
      }
    },
    {
      "account_id": "1795278261246132",
      "account_name": "McQuiston Dental & Aesthetics",
      "status": "active",
      "last_7_days": {
        "spend": 400.46,
        "impressions": 9810,
        "clicks": 632,
        "cpc": 0.633639,
        "cpm": 40.821611,
        "ctr": 6.442406,
        "reach": 6563,
        "leads": 21,
        "cost_per_lead": 19.069524
      },
      "last_30_days": {
        "spend": 1541.08,
        "impressions": 37138,
        "clicks": 2201,
        "cpc": 0.700173,
        "cpm": 41.496042,
        "ctr": 5.926544,
        "reach": 16975,
        "leads": 132,
        "cost_per_lead": 11.674848
      }
    },
    {
      "account_id": "873011548816017",
      "account_name": "Michel Medspa - Dana Point",
      "status": "active",
      "last_7_days": {
        "spend": 152.46,
        "impressions": 1443,
        "clicks": 38,
        "cpc": 4.012105,
        "cpm": 105.654886,
        "ctr": 2.633403,
        "reach": 1059,
        "leads": 2,
        "cost_per_lead": 76.23
      },
      "last_30_days": {
        "spend": 3063.07,
        "impressions": 54478,
        "clicks": 1464,
        "cpc": 2.092261,
        "cpm": 56.225816,
        "ctr": 2.687323,
        "reach": 21478,
        "leads": 57,
        "cost_per_lead": 53.73807
      }
    },
    {
      "account_id": "624982636077867",
      "account_name": "Precision Weight Loss",
      "status": "active",
      "last_7_days": {
        "spend": 585.55,
        "impressions": 13522,
        "clicks": 609,
        "cpc": 0.961494,
        "cpm": 43.303505,
        "ctr": 4.503772,
        "reach": 8950,
        "leads": 26,
        "cost_per_lead": 22.521154
      },
      "last_30_days": {
        "spend": 2122.3,
        "impressions": 50484,
        "clicks": 2383,
        "cpc": 0.8906,
        "cpm": 42.039062,
        "ctr": 4.720307,
        "reach": 24723,
        "leads": 75,
        "cost_per_lead": 28.297333
      }
    },
    {
      "account_id": "664585076610096",
      "account_name": "Prestige Laser & Skin Clinic",
      "status": "active",
      "last_7_days": {
        "spend": 381.84,
        "impressions": 23237,
        "clicks": 801,
        "cpc": 0.476704,
        "cpm": 16.432414,
        "ctr": 3.447089,
        "reach": 13513,
        "leads": 31,
        "cost_per_lead": 12.317419
      },
      "last_30_days": {
        "spend": 1526.84,
        "impressions": 92941,
        "clicks": 2992,
        "cpc": 0.510307,
        "cpm": 16.428057,
        "ctr": 3.219247,
        "reach": 33998,
        "leads": 116,
        "cost_per_lead": 13.162414
      }
    },
    {
      "account_id": "510154927988642",
      "account_name": "Servedia - B2B - CHF",
      "status": "active",
      "last_7_days": {
        "spend": 6274.61,
        "impressions": 298402,
        "clicks": 1580,
        "cpc": 3.971272,
        "cpm": 21.027372,
        "ctr": 0.529487,
        "reach": 246167,
        "leads": 74,
        "cost_per_lead": 84.792027
      },
      "last_30_days": {
        "spend": 21911.06,
        "impressions": 1170851,
        "clicks": 6515,
        "cpc": 3.363171,
        "cpm": 18.71379,
        "ctr": 0.556433,
        "reach": 753763,
        "leads": 282,
        "cost_per_lead": 77.698794
      }
    },
    {
      "account_id": "3896645637242883",
      "account_name": "Servedia - Hiring - CHF",
      "status": "no_data",
      "last_7_days": {
        "spend": 0.0,
        "impressions": 0,
        "clicks": 0,
        "cpc": 0.0,
        "cpm": 0.0,
        "ctr": 0.0,
        "reach": 0,
        "leads": 0,
        "cost_per_lead": 0
      },
      "last_30_days": {
        "spend": 0.0,
        "impressions": 0,
        "clicks": 0,
        "cpc": 0.0,
        "cpm": 0.0,
        "ctr": 0.0,
        "reach": 0,
        "leads": 0,
        "cost_per_lead": 0
      }
    },
    {
      "account_id": "524158318772571",
      "account_name": "Skinholic(2025) - AIMOP",
      "status": "no_data",
      "last_7_days": {
        "spend": 0.0,
        "impressions": 0,
        "clicks": 0,
        "cpc": 0.0,
        "cpm": 0.0,
        "ctr": 0.0,
        "reach": 0,
        "leads": 0,
        "cost_per_lead": 0
      },
      "last_30_days": {
        "spend": 170.24,
        "impressions": 11615,
        "clicks": 509,
        "cpc": 0.33446,
        "cpm": 14.656909,
        "ctr": 4.382264,
        "reach": 4565,
        "leads": 0,
        "cost_per_lead": 0
      }
    },
    {
      "account_id": "4140577459602242",
      "account_name": "Skinsation Aesthetics - SA",
      "status": "active",
      "last_7_days": {
        "spend": 534.59,
        "impressions": 8619,
        "clicks": 278,
        "cpc": 1.922986,
        "cpm": 62.024597,
        "ctr": 3.225432,
        "reach": 4463,
        "leads": 9,
        "cost_per_lead": 59.398889
      },
      "last_30_days": {
        "spend": 1743.36,
        "impressions": 42282,
        "clicks": 1555,
        "cpc": 1.121132,
        "cpm": 41.23173,
        "ctr": 3.677688,
        "reach": 16709,
        "leads": 56,
        "cost_per_lead": 31.131429
      }
    },
    {
      "account_id": "502049325517257",
      "account_name": "The MAC OKC",
      "status": "active",
      "last_7_days": {
        "spend": 818.61,
        "impressions": 10479,
        "clicks": 562,
        "cpc": 1.456601,
        "cpm": 78.119095,
        "ctr": 5.363107,
        "reach": 8715,
        "leads": 19,
        "cost_per_lead": 43.084737
      },
      "last_30_days": {
        "spend": 3805.74,
        "impressions": 58027,
        "clicks": 2904,
        "cpc": 1.310517,
        "cpm": 65.585676,
        "ctr": 5.004567,
        "reach": 38091,
        "leads": 118,
        "cost_per_lead": 32.252034
      }
    },
    {
      "account_id": "1603057050496702",
      "account_name": "Thorpe Wellness 2.0",
      "status": "no_data",
      "last_7_days": {
        "spend": 0.0,
        "impressions": 0,
        "clicks": 0,
        "cpc": 0.0,
        "cpm": 0.0,
        "ctr": 0.0,
        "reach": 0,
        "leads": 0,
        "cost_per_lead": 0
      },
      "last_30_days": {
        "spend": 0.0,
        "impressions": 0,
        "clicks": 0,
        "cpc": 0.0,
        "cpm": 0.0,
        "ctr": 0.0,
        "reach": 0,
        "leads": 0,
        "cost_per_lead": 0
      }
    },
    {
      "account_id": "1242208869314128",
      "account_name": "Transformations Esthetics & Wellness",
      "status": "active",
      "last_7_days": {
        "spend": 393.88,
        "impressions": 9992,
        "clicks": 344,
        "cpc": 1.145,
        "cpm": 39.419536,
        "ctr": 3.442754,
        "reach": 4470,
        "leads": 12,
        "cost_per_lead": 32.823333
      },
      "last_30_days": {
        "spend": 1519.47,
        "impressions": 64092,
        "clicks": 1980,
        "cpc": 0.767409,
        "cpm": 23.707639,
        "ctr": 3.089309,
        "reach": 25603,
        "leads": 43,
        "cost_per_lead": 35.336512
      }
    },
    {
      "account_id": "982882907385968",
      "account_name": "Transformative Wellness",
      "status": "active",
      "last_7_days": {
        "spend": 444.63,
        "impressions": 8779,
        "clicks": 217,
        "cpc": 2.048986,
        "cpm": 50.646999,
        "ctr": 2.471808,
        "reach": 4209,
        "leads": 12,
        "cost_per_lead": 37.0525
      },
      "last_30_days": {
        "spend": 897.6,
        "impressions": 16694,
        "clicks": 439,
        "cpc": 2.044647,
        "cpm": 53.767821,
        "ctr": 2.629687,
        "reach": 6670,
        "leads": 26,
        "cost_per_lead": 34.523077
      }
    },
    {
      "account_id": "1488627745841127",
      "account_name": "Vital Life",
      "status": "active",
      "last_7_days": {
        "spend": 401.6,
        "impressions": 10341,
        "clicks": 369,
        "cpc": 1.088347,
        "cpm": 38.835703,
        "ctr": 3.56832,
        "reach": 5011,
        "leads": 12,
        "cost_per_lead": 33.466667
      },
      "last_30_days": {
        "spend": 1454.53,
        "impressions": 56753,
        "clicks": 2485,
        "cpc": 0.585324,
        "cpm": 25.62913,
        "ctr": 4.378623,
        "reach": 26611,
        "leads": 71,
        "cost_per_lead": 20.486338
      }
    },
    {
      "account_id": "894241480205692",
      "account_name": "Wellness Herbal - SA",
      "status": "active",
      "last_7_days": {
        "spend": 384.88,
        "impressions": 10564,
        "clicks": 279,
        "cpc": 1.379498,
        "cpm": 36.433169,
        "ctr": 2.641045,
        "reach": 6957,
        "leads": 14,
        "cost_per_lead": 27.491429
      },
      "last_30_days": {
        "spend": 1520.88,
        "impressions": 41633,
        "clicks": 1274,
        "cpc": 1.193783,
        "cpm": 36.530637,
        "ctr": 3.060073,
        "reach": 19836,
        "leads": 64,
        "cost_per_lead": 23.76375
      }
    },
    {
      "account_id": "1121472973270105",
      "account_name": "Wilmarwell LLC",
      "status": "no_data",
      "last_7_days": {
        "spend": 0.0,
        "impressions": 0,
        "clicks": 0,
        "cpc": 0.0,
        "cpm": 0.0,
        "ctr": 0.0,
        "reach": 0,
        "leads": 0,
        "cost_per_lead": 0
      },
      "last_30_days": {
        "spend": 0.0,
        "impressions": 0,
        "clicks": 0,
        "cpc": 0.0,
        "cpm": 0.0,
        "ctr": 0.0,
        "reach": 0,
        "leads": 0,
        "cost_per_lead": 0
      }
    },
    {
      "account_id": "1400828974006140",
      "account_name": "beautyandwellnesscenter",
      "status": "active",
      "last_7_days": {
        "spend": 390.7,
        "impressions": 18114,
        "clicks": 724,
        "cpc": 0.539641,
        "cpm": 21.568952,
        "ctr": 3.996908,
        "reach": 10272,
        "leads": 41,
        "cost_per_lead": 9.529268
      },
      "last_30_days": {
        "spend": 1525.31,
        "impressions": 72726,
        "clicks": 2839,
        "cpc": 0.53727,
        "cpm": 20.97338,
        "ctr": 3.903693,
        "reach": 24765,
        "leads": 130,
        "cost_per_lead": 11.733154
      }
    },
    {
      "account_id": "1464948185130737",
      "account_name": "dailey aesthetics",
      "status": "active",
      "last_7_days": {
        "spend": 218.21,
        "impressions": 3852,
        "clicks": 149,
        "cpc": 1.464497,
        "cpm": 56.648494,
        "ctr": 3.86812,
        "reach": 2824,
        "leads": 4,
        "cost_per_lead": 54.5525
      },
      "last_30_days": {
        "spend": 225.67,
        "impressions": 3948,
        "clicks": 153,
        "cpc": 1.474967,
        "cpm": 57.160588,
        "ctr": 3.87538,
        "reach": 2874,
        "leads": 4,
        "cost_per_lead": 56.4175
      }
    },
    {
      "account_id": "890702377151942",
      "account_name": "servedia - gencore aesthetic",
      "status": "active",
      "last_7_days": {
        "spend": 499.16,
        "impressions": 9681,
        "clicks": 387,
        "cpc": 1.289819,
        "cpm": 51.560789,
        "ctr": 3.997521,
        "reach": 4629,
        "leads": 15,
        "cost_per_lead": 33.277333
      },
      "last_30_days": {
        "spend": 1827.5,
        "impressions": 43430,
        "clicks": 2007,
        "cpc": 0.910563,
        "cpm": 42.079208,
        "ctr": 4.62123,
        "reach": 12855,
        "leads": 81,
        "cost_per_lead": 22.561728
      }
    }
  ],
  "total_accounts": 37,
  "accounts_with_data": 28,
  "accounts_with_errors": 0,
  "errors": [],
  "pulled_at": "2026-04-05T23:26:28Z"
}